flatly/__init__.py
flatly/conf.py
flatly/exceptions.py
flatly/helpers.py
flatly/urls.py
flatly/views.py
django_flatly-0.3.1.dist-info/LICENSE
django_flatly-0.3.1.dist-info/METADATA
django_flatly-0.3.1.dist-info/WHEEL
django_flatly-0.3.1.dist-info/top_level.txt
django_flatly-0.3.1.dist-info/RECORD
